{
    "created_time": "2020-01-11T13:27:50Z",
    "files": [
        {
            "attachment_folder": "",
            "attachments": [
            ],
            "created_time": "2020-01-11T13:28:23Z",
            "modified_time": "2020-01-11T13:28:29Z",
            "name": "Blender引擎.md",
            "tags": [
            ]
        },
        {
            "attachment_folder": "",
            "attachments": [
            ],
            "created_time": "2020-02-05T04:20:42Z",
            "modified_time": "2020-02-07T11:35:25Z",
            "name": "Blender快捷键.md",
            "tags": [
            ]
        },
        {
            "attachment_folder": "",
            "attachments": [
            ],
            "created_time": "2020-02-07T11:35:34Z",
            "modified_time": "2020-02-07T11:37:13Z",
            "name": "Blender坑.md",
            "tags": [
            ]
        },
        {
            "attachment_folder": "",
            "attachments": [
            ],
            "created_time": "2020-02-07T15:19:00Z",
            "modified_time": "2020-02-07T15:42:11Z",
            "name": "Blender贴图.md",
            "tags": [
            ]
        },
        {
            "attachment_folder": "",
            "attachments": [
            ],
            "created_time": "2020-02-22T03:00:04Z",
            "modified_time": "2020-02-22T06:09:01Z",
            "name": "Blender材质.md",
            "tags": [
            ]
        },
        {
            "attachment_folder": "",
            "attachments": [
            ],
            "created_time": "2020-02-26T15:24:25Z",
            "modified_time": "2020-02-26T15:26:37Z",
            "name": "Blender建模技巧.md",
            "tags": [
            ]
        }
    ],
    "sub_directories": [
    ],
    "version": "1"
}
