{
    "created_time": "2018-04-22T03:15:55Z",
    "files": [
        {
            "attachment_folder": "",
            "attachments": [
            ],
            "created_time": "2017-10-16T06:32:18Z",
            "modified_time": "2017-10-16T06:37:29Z",
            "name": "vector.md",
            "tags": [
            ]
        },
        {
            "attachment_folder": "",
            "attachments": [
            ],
            "created_time": "2017-10-16T07:29:24Z",
            "modified_time": "2017-10-16T10:08:33Z",
            "name": "C++中的STL中map用法详解.md",
            "tags": [
            ]
        },
        {
            "attachment_folder": "",
            "attachments": [
            ],
            "created_time": "2017-10-16T07:35:49Z",
            "modified_time": "2017-10-16T07:37:14Z",
            "name": "map用法整理.md",
            "tags": [
            ]
        },
        {
            "attachment_folder": "",
            "attachments": [
            ],
            "created_time": "2017-10-17T01:25:00Z",
            "modified_time": "2017-10-17T01:25:00Z",
            "name": "queue.md",
            "tags": [
            ]
        },
        {
            "attachment_folder": "",
            "attachments": [
            ],
            "created_time": "2019-06-06T05:12:23Z",
            "modified_time": "2019-06-06T07:21:07Z",
            "name": "STL中的多线程.md",
            "tags": [
            ]
        }
    ],
    "sub_directories": [
    ],
    "version": "1"
}
